examinerview/Controller.py
examinerview/__init__.py
examinerview/__main__.py
examinerview/classes/Event.py
examinerview/classes/Timeline.py
examinerview/classes/__init__.py
examinerview/template/__init__.py
examinerview/template/index.html
examinerview-1.0.2.dist-info/LICENSE.md
examinerview-1.0.2.dist-info/METADATA
examinerview-1.0.2.dist-info/WHEEL
examinerview-1.0.2.dist-info/entry_points.txt
examinerview-1.0.2.dist-info/top_level.txt
examinerview-1.0.2.dist-info/RECORD
