Metadata-Version: 2.1
Name: examinerview
Version: 1.0.2
Summary: Create visual timelines for forensic investigations
Home-page: https://github.com/5f0ne/examinerview
Author: 5f0
License: MIT
Classifier: Operating System :: OS Independent 
Classifier: Programming Language :: Python :: 3 
Classifier: License :: OSI Approved :: MIT License 
License-File: LICENSE.md
